anatomic_locations/__init__.py
anatomic_locations/cli.py
anatomic_locations/config.py
anatomic_locations/index.py
anatomic_locations/models/__init__.py
anatomic_locations/models/enums.py
anatomic_locations/models/location.py
anatomic_locations-0.2.0.dist-info/WHEEL
anatomic_locations-0.2.0.dist-info/entry_points.txt
anatomic_locations-0.2.0.dist-info/METADATA
anatomic_locations-0.2.0.dist-info/RECORD
