Metadata-Version: 2.3
Name: anatomic-locations
Version: 0.2.0
Summary: Anatomic location ontology navigation
Requires-Dist: oidm-common
Requires-Dist: asyncer>=0.0.2
Requires-Dist: click>=8.0
Requires-Dist: duckdb>=1.0
Requires-Dist: loguru>=0.7
Requires-Dist: pydantic-settings>=2.9
Requires-Dist: rich>=13.0
Requires-Dist: openai>=1.0 ; extra == 'openai'
Requires-Dist: pytest>=8.0 ; extra == 'test'
Requires-Dist: pytest-asyncio>=0.24 ; extra == 'test'
Requires-Dist: openai>=1.0 ; extra == 'test'
Requires-Dist: pydantic-ai-slim>=0.1 ; extra == 'test'
Requires-Python: >=3.11
Provides-Extra: openai
Provides-Extra: test
